spacectl/__init__.py
spacectl/main.py
spacectl/command/__init__.py
spacectl/command/api_resource.py
spacectl/command/apply.py
spacectl/command/config.py
spacectl/command/execute.py
spacectl/command/template.py
spacectl/command/version.py
spacectl/conf/__init__.py
spacectl/conf/global_conf.py
spacectl/conf/my_conf.py
spacectl/lib/__init__.py
spacectl/lib/output.py
spacectl/lib/template.py
spacectl/lib/apply/__init__.py
spacectl/lib/apply/dot_dict_list.py
spacectl/lib/apply/store.py
spacectl/lib/apply/task.py
spacectl/lib/apply/task_manager.py
spacectl/lib/parser/__init__.py
spacectl/lib/parser/apply_jinja.py
spacectl/lib/parser/apply_manifest.py
spacectl/lib/parser/default.py
spacectl/modules/__init__.py
spacectl/modules/export_google_sheets/__init__.py
spacectl/modules/export_google_sheets/export_google_sheets_task.py
spacectl/modules/resource/__init__.py
spacectl/modules/resource/resource_task.py
spacectl/modules/resource/validate.py
spacectl/modules/shell/__init__.py
spacectl/modules/shell/shell_task.py
spacectl/template/identity.Domain.yml
spacectl/template/identity.Project.yml
spacectl/template/inventory.Server.yml
foretctl-1.1.1.dist-info/METADATA
foretctl-1.1.1.dist-info/WHEEL
foretctl-1.1.1.dist-info/entry_points.txt
foretctl-1.1.1.dist-info/top_level.txt
foretctl-1.1.1.dist-info/RECORD
