Metadata-Version: 2.1
Name: foretctl
Version: 1.1.1
Summary: SpaceONE Command Line Interface
Home-page: https://www.spaceone.dev/
Author: MEGAZONE SpaceONE Team
Author-email: admin@spaceone.dev
License: Apache License 2.0
Platform: UNKNOWN
Requires-Dist: spaceone-core
Requires-Dist: spaceone-api
Requires-Dist: Click
Requires-Dist: tabulate
Requires-Dist: jinja2
Requires-Dist: gspread
Requires-Dist: pandas
